pcap_fuzzer/__init__.py
pcap_fuzzer/__main__.py
pcap_fuzzer/arg_types.py
pcap_fuzzer/pcap_fuzzer.py
pcap_fuzzer/packet/ARP.py
pcap_fuzzer/packet/BOOTP.py
pcap_fuzzer/packet/CoAP.py
pcap_fuzzer/packet/DNS.py
pcap_fuzzer/packet/HTTP_Request.py
pcap_fuzzer/packet/ICMP.py
pcap_fuzzer/packet/IGMP.py
pcap_fuzzer/packet/IGMPv3mr.py
pcap_fuzzer/packet/IPv4.py
pcap_fuzzer/packet/IPv6.py
pcap_fuzzer/packet/Packet.py
pcap_fuzzer/packet/TCP.py
pcap_fuzzer/packet/Transport.py
pcap_fuzzer/packet/UDP.py
pcap_fuzzer/packet/__init__.py
pcap_fuzzer/packet/mDNS.py
pcap_fuzzer-0.5.0.dist-info/licenses/LICENSE
pcap_fuzzer-0.5.0.dist-info/METADATA
pcap_fuzzer-0.5.0.dist-info/WHEEL
pcap_fuzzer-0.5.0.dist-info/entry_points.txt
pcap_fuzzer-0.5.0.dist-info/top_level.txt
pcap_fuzzer-0.5.0.dist-info/RECORD
