Metadata-Version: 2.4
Name: pcap-fuzzer
Version: 0.5.0
Summary: Randomly edit packet fields in a PCAP file.
Author-email: François De Keersmaeker <francois.dekeersmaeker+github@proton.me>
Maintainer-email: François De Keersmaeker <francois.dekeersmaeker+github@proton.me>
License-Expression: GPL-3.0-or-later
Project-URL: Homepage, https://github.com/smart-home-network-security/pcap-fuzzer
Project-URL: Source, https://github.com/smart-home-network-security/pcap-fuzzer
Keywords: network,dns,unbound
Classifier: Development Status :: 3 - Alpha
Classifier: Programming Language :: Python :: 3
Classifier: Programming Language :: Python :: 3.8
Classifier: Programming Language :: Python :: 3.9
Classifier: Programming Language :: Python :: 3.10
Classifier: Programming Language :: Python :: 3.11
Classifier: Programming Language :: Python :: 3.12
Classifier: Programming Language :: Python :: 3 :: Only
Classifier: Operating System :: OS Independent
Requires-Python: >=3.8
License-File: LICENSE
Requires-Dist: scapy==2.6.1
Dynamic: license-file
